Metadata-Version: 2.4
Name: sea_urchin
Version: 1.1
Summary: Python tools for post-processing MD trajectories and local structure analysis
Author-email: Materials Theory Group <dgprendergast@lbl.gov>
Maintainer-email: Materials Theory Group <dgprendergast@lbl.gov>
License: Apache-2.0
Project-URL: Homepage, https://gitlab.com/electrolyte-machine/sea_urchin
Project-URL: Repository, https://gitlab.com/electrolyte-machine/sea_urchin.git
Project-URL: Documentation, https://gitlab.com/electrolyte-machine/sea_urchin
Project-URL: Bug Reports, https://gitlab.com/electrolyte-machine/sea_urchin/-/issues
Keywords: molecular dynamics,structure analysis,machine learning,clustering
Classifier: Development Status :: 5 - Production/Stable
Classifier: Intended Audience :: Science/Research
Classifier: License :: OSI Approved :: Apache Software License
Classifier: Operating System :: OS Independent
Classifier: Programming Language :: Python :: 3
Classifier: Programming Language :: Python :: 3.8
Classifier: Programming Language :: Python :: 3.9
Classifier: Programming Language :: Python :: 3.10
Classifier: Programming Language :: Python :: 3.11
Classifier: Topic :: Scientific/Engineering :: Chemistry
Classifier: Topic :: Scientific/Engineering :: Physics
Requires-Python: >=3.8
License-File: LICENSE
Requires-Dist: numpy>=1.20.0
Requires-Dist: scipy>=1.7.0
Requires-Dist: ase>=3.20.0
Requires-Dist: pandas>=1.3.0
Requires-Dist: joblib>=1.0.0
Requires-Dist: dill>=0.3.0
Requires-Dist: psutil>=5.8.0
Requires-Dist: networkx>=2.6.0
Requires-Dist: mdtraj>=1.9.0
Requires-Dist: hdbscan>=0.8.0
Requires-Dist: umap-learn>=0.5.0
Requires-Dist: matplotlib>=3.3.0
Requires-Dist: seaborn>=0.11.0
Requires-Dist: colorcet>=2.0.0
Requires-Dist: scikit-learn>=1.0.0
Requires-Dist: colorama>=0.4.0
Requires-Dist: numba>=0.56.0
Dynamic: license-file
